haadb/__init__.py
haadb/haadb.py
haadb-1.0.0.dist-info/LICENSE
haadb-1.0.0.dist-info/METADATA
haadb-1.0.0.dist-info/WHEEL
haadb-1.0.0.dist-info/top_level.txt
haadb-1.0.0.dist-info/RECORD
