Metadata-Version: 2.1
Name: haadb
Version: 1.0.0
Summary: Hive-as-a-DB SDK for Python
Home-page: https://github.com/rmaniego/haadb
Download-URL: https://github.com/rmaniego/haadb/archive/v1.0.tar.gz
Author: Rodney Maniego Jr.
Author-email: rodney.maniegojr@gmail.com
License: MIT
Keywords: haadb,hive,blockchain,api,sdk,database
Classifier: Development Status :: 5 - Production/Stable
Classifier: Intended Audience :: Developers
Classifier: Topic :: Software Development :: Build Tools
Classifier: License :: OSI Approved :: MIT License
Classifier: Programming Language :: Python :: 3
Requires-Python: >=3.9
License-File: LICENSE
Requires-Dist: hive-nektar
Requires-Dist: cryptography
